setup_requirements.py
setup_requirements-1.2.dist-info/LICENSE
setup_requirements-1.2.dist-info/METADATA
setup_requirements-1.2.dist-info/WHEEL
setup_requirements-1.2.dist-info/top_level.txt
setup_requirements-1.2.dist-info/RECORD
