Metadata-Version: 2.1
Name: setup-requirements
Version: 1.2
Summary: Add requirements.txt automatically to wheel dependencies
Home-page: https://github.com/mbachry/setup-requirements
Author: Marcin Bachry
Author-email: hegel666@gmail.com
License: MIT
Platform: unix
Platform: linux
Platform: osx
Platform: cygwin
Platform: win32
Classifier: Development Status :: 4 - Beta
Classifier: Intended Audience :: Developers
Classifier: License :: OSI Approved :: MIT License
Classifier: Programming Language :: Cython
Classifier: Programming Language :: Python
Classifier: Programming Language :: Python :: 3
Classifier: Programming Language :: Python :: 3 :: Only
Classifier: Programming Language :: Python :: 3.9
Classifier: Programming Language :: Python :: Implementation :: CPython
Requires-Python: >=3.9
Requires-Dist: wheel
